snorlax/__init__.py
snorlax/common.py
snorlaxse-0.0.3.dist-info/METADATA
snorlaxse-0.0.3.dist-info/RECORD
snorlaxse-0.0.3.dist-info/WHEEL
snorlaxse-0.0.3.dist-info/top_level.txt
