Metadata-Version: 2.1
Name: snorlaxse
Version: 0.0.3
Summary: upload some self useful code
Home-page: https://github.com/Captainzj/snorlax_package.git
Author: snorlaxse
Author-email: 841145636@qq.com
License: UNKNOWN
Platform: UNKNOWN
Classifier: Programming Language :: Python :: 3
Classifier: License :: OSI Approved :: MIT License
Classifier: Operating System :: OS Independent
